odoo/addons/base_gs1_barcode/README.rst
odoo/addons/base_gs1_barcode/__init__.py
odoo/addons/base_gs1_barcode/__manifest__.py
odoo/addons/base_gs1_barcode/data/gs1_barcode.csv
odoo/addons/base_gs1_barcode/i18n/am.po
odoo/addons/base_gs1_barcode/i18n/ar.po
odoo/addons/base_gs1_barcode/i18n/base_gs1_barcode.pot
odoo/addons/base_gs1_barcode/i18n/bg.po
odoo/addons/base_gs1_barcode/i18n/bs.po
odoo/addons/base_gs1_barcode/i18n/ca.po
odoo/addons/base_gs1_barcode/i18n/ca_ES.po
odoo/addons/base_gs1_barcode/i18n/cs.po
odoo/addons/base_gs1_barcode/i18n/da.po
odoo/addons/base_gs1_barcode/i18n/de.po
odoo/addons/base_gs1_barcode/i18n/el_GR.po
odoo/addons/base_gs1_barcode/i18n/en_GB.po
odoo/addons/base_gs1_barcode/i18n/es.po
odoo/addons/base_gs1_barcode/i18n/es_AR.po
odoo/addons/base_gs1_barcode/i18n/es_BO.po
odoo/addons/base_gs1_barcode/i18n/es_CL.po
odoo/addons/base_gs1_barcode/i18n/es_CO.po
odoo/addons/base_gs1_barcode/i18n/es_CR.po
odoo/addons/base_gs1_barcode/i18n/es_DO.po
odoo/addons/base_gs1_barcode/i18n/es_EC.po
odoo/addons/base_gs1_barcode/i18n/es_ES.po
odoo/addons/base_gs1_barcode/i18n/es_MX.po
odoo/addons/base_gs1_barcode/i18n/es_PE.po
odoo/addons/base_gs1_barcode/i18n/es_PY.po
odoo/addons/base_gs1_barcode/i18n/es_VE.po
odoo/addons/base_gs1_barcode/i18n/et.po
odoo/addons/base_gs1_barcode/i18n/eu.po
odoo/addons/base_gs1_barcode/i18n/fa.po
odoo/addons/base_gs1_barcode/i18n/fi.po
odoo/addons/base_gs1_barcode/i18n/fr.po
odoo/addons/base_gs1_barcode/i18n/fr_CA.po
odoo/addons/base_gs1_barcode/i18n/fr_CH.po
odoo/addons/base_gs1_barcode/i18n/fr_FR.po
odoo/addons/base_gs1_barcode/i18n/gl.po
odoo/addons/base_gs1_barcode/i18n/gl_ES.po
odoo/addons/base_gs1_barcode/i18n/he.po
odoo/addons/base_gs1_barcode/i18n/hr.po
odoo/addons/base_gs1_barcode/i18n/hr_HR.po
odoo/addons/base_gs1_barcode/i18n/hu.po
odoo/addons/base_gs1_barcode/i18n/id.po
odoo/addons/base_gs1_barcode/i18n/it.po
odoo/addons/base_gs1_barcode/i18n/ja.po
odoo/addons/base_gs1_barcode/i18n/ko.po
odoo12_addon_base_gs1_barcode-12.0.1.1.1.dist-info/METADATA
odoo12_addon_base_gs1_barcode-12.0.1.1.1.dist-info/WHEEL
odoo12_addon_base_gs1_barcode-12.0.1.1.1.dist-info/top_level.txt
odoo12_addon_base_gs1_barcode-12.0.1.1.1.dist-info/RECORD
